{
  "routes": [
    {
      "vehicle_id": 0,
      "vehicle_name": "Truck-01-c2",
      "capacity_used": 0.0,
      "capacity_max": 10000.0,
      "capacity_utilization": 0.0,
      "distance_m": 88324.70000000003,
      "time_s": 7740.1,
      "stops_by_id": [
        0,
        28,
        27,
        26,
        22,
        23,
        24,
        25,
        21,
        66,
        1,
        7,
        16,
        15,
        14,
        13,
        70,
        11,
        10,
        19,
        2,
        3,
        17,
        0
      ]
    }
  ]
}