{
  "total_cost": 2239257.0,
  "total_time": 197.76288203792384,
  "routes": [
    {
      "vehicle_id": 1,
      "vehicle_name": "Truck-01",
      "distance_m": 2742.0,
      "time_s": 197.76288203792384,
      "route_cost": 2239257.0,
      "stops_by_id": [
        1,
        5,
        6,
        7,
        9,
        8,
        10,
        11,
        12,
        15,
        13,
        14,
        24,
        23,
        25,
        22,
        26,
        27,
        28,
        29,
        30,
        31,
        32,
        33,
        34,
        61,
        118,
        117,
        115,
        116,
        86,
        85,
        65,
        66,
        64,
        63,
        62,
        60,
        43,
        42,
        41,
        40,
        39,
        38,
        35,
        36,
        37,
        50,
        51,
        52,
        49,
        48,
        47,
        53,
        54,
        46,
        55,
        56,
        57,
        45,
        44,
        59,
        58,
        68,
        69,
        67,
        70,
        71,
        72,
        73,
        74,
        75,
        77,
        78,
        76,
        84,
        87,
        113,
        114,
        111,
        112,
        110,
        108,
        109,
        88,
        83,
        82,
        79,
        80,
        81,
        89,
        90,
        91,
        92,
        93,
        94,
        95,
        96,
        97,
        98,
        99,
        100,
        101,
        102,
        103,
        104,
        105,
        106,
        107,
        174,
        173,
        171,
        172,
        170,
        169,
        168,
        167,
        166,
        165,
        164,
        163,
        162,
        161,
        175,
        160,
        159,
        158,
        157,
        119,
        120,
        121,
        122,
        123,
        124,
        125,
        126,
        127,
        128,
        21,
        20,
        19,
        18,
        17,
        133,
        132,
        131,
        130,
        129,
        154,
        155,
        153,
        156,
        152,
        151,
        177,
        176,
        181,
        182,
        183,
        184,
        185,
        186,
        187,
        188,
        189,
        190,
        191,
        192,
        193,
        197,
        194,
        195,
        196,
        201,
        198,
        199,
        145,
        146,
        179,
        180,
        178,
        150,
        149,
        139,
        140,
        141,
        148,
        147,
        142,
        143,
        144,
        200,
        202,
        203,
        204,
        205,
        206,
        208,
        207,
        212,
        211,
        214,
        213,
        215,
        218,
        216,
        217,
        220,
        221,
        222,
        219,
        223,
        224,
        225,
        226,
        227,
        234,
        235,
        236,
        233,
        232,
        237,
        238,
        231,
        246,
        239,
        240,
        245,
        247,
        244,
        241,
        243,
        242,
        2,
        280,
        3,
        279,
        278,
        248,
        249,
        250,
        251,
        230,
        229,
        228,
        210,
        209,
        252,
        253,
        254,
        255,
        256,
        257,
        258,
        259,
        260,
        261,
        262,
        263,
        264,
        265,
        266,
        138,
        137,
        267,
        136,
        268,
        269,
        135,
        134,
        270,
        16,
        271,
        272,
        273,
        274,
        275,
        276,
        277,
        4,
        1
      ],
      "legs": [
        {
          "from": 1,
          "to": 5,
          "distance_m": 33.0,
          "time_s": 2.61976397873875
        },
        {
          "from": 5,
          "to": 6,
          "distance_m": 10.0,
          "time_s": 0.6601493545824352
        },
        {
          "from": 6,
          "to": 7,
          "distance_m": 16.0,
          "time_s": 1.2746915534937224
        },
        {
          "from": 7,
          "to": 9,
          "distance_m": 11.0,
          "time_s": 0.8446258038750806
        },
        {
          "from": 9,
          "to": 8,
          "distance_m": 8.0,
          "time_s": 0.6426605295320756
        },
        {
          "from": 8,
          "to": 10,
          "distance_m": 8.0,
          "time_s": 0.5811708758627979
        },
        {
          "from": 10,
          "to": 11,
          "distance_m": 8.0,
          "time_s": 0.5603157562253531
        },
        {
          "from": 11,
          "to": 12,
          "distance_m": 8.0,
          "time_s": 0.5333671530707568
        },
        {
          "from": 12,
          "to": 15,
          "distance_m": 11.0,
          "time_s": 0.7488429372546246
        },
        {
          "from": 15,
          "to": 13,
          "distance_m": 8.0,
          "time_s": 0.5735682610309817
        },
        {
          "from": 13,
          "to": 14,
          "distance_m": 8.0,
          "time_s": 0.6188538406322658
        },
        {
          "from": 14,
          "to": 24,
          "distance_m": 16.0,
          "time_s": 1.0937357123849922
        },
        {
          "from": 24,
          "to": 23,
          "distance_m": 8.0,
          "time_s": 0.5932701397097052
        },
        {
          "from": 23,
          "to": 25,
          "distance_m": 8.0,
          "time_s": 0.5907970112631028
        },
        {
          "from": 25,
          "to": 22,
          "distance_m": 8.0,
          "time_s": 0.5808670371213306
        },
        {
          "from": 22,
          "to": 26,
          "distance_m": 8.0,
          "time_s": 0.6045245410630987
        },
        {
          "from": 26,
          "to": 27,
          "distance_m": 8.0,
          "time_s": 0.588722588656534
        },
        {
          "from": 27,
          "to": 28,
          "distance_m": 8.0,
          "time_s": 0.5536007614118256
        },
        {
          "from": 28,
          "to": 29,
          "distance_m": 11.0,
          "time_s": 0.7692267651316631
        },
        {
          "from": 29,
          "to": 30,
          "distance_m": 14.0,
          "time_s": 0.9595803969434498
        },
        {
          "from": 30,
          "to": 31,
          "distance_m": 8.0,
          "time_s": 0.6332764154662978
        },
        {
          "from": 31,
          "to": 32,
          "distance_m": 8.0,
          "time_s": 0.5290917010433008
        },
        {
          "from": 32,
          "to": 33,
          "distance_m": 15.0,
          "time_s": 1.0928538128759586
        },
        {
          "from": 33,
          "to": 34,
          "distance_m": 13.0,
          "time_s": 1.0157718362617731
        },
        {
          "from": 34,
          "to": 61,
          "distance_m": 57.0,
          "time_s": 4.3380589441482
        },
        {
          "from": 61,
          "to": 118,
          "distance_m": 8.0,
          "time_s": 0.5771091355895269
        },
        {
          "from": 118,
          "to": 117,
          "distance_m": 8.0,
          "time_s": 0.5663231267307711
        },
        {
          "from": 117,
          "to": 115,
          "distance_m": 8.0,
          "time_s": 0.5451610506475543
        },
        {
          "from": 115,
          "to": 116,
          "distance_m": 8.0,
          "time_s": 0.5974189411205856
        },
        {
          "from": 116,
          "to": 86,
          "distance_m": 8.0,
          "time_s": 0.4937443183199861
        },
        {
          "from": 86,
          "to": 85,
          "distance_m": 8.0,
          "time_s": 0.6250577669970736
        },
        {
          "from": 85,
          "to": 65,
          "distance_m": 8.0,
          "time_s": 0.5183239761524531
        },
        {
          "from": 65,
          "to": 66,
          "distance_m": 8.0,
          "time_s": 0.549074434986819
        },
        {
          "from": 66,
          "to": 64,
          "distance_m": 11.0,
          "time_s": 0.8572901779144454
        },
        {
          "from": 64,
          "to": 63,
          "distance_m": 8.0,
          "time_s": 0.5443990989234938
        },
        {
          "from": 63,
          "to": 62,
          "distance_m": 8.0,
          "time_s": 0.5570648276718001
        },
        {
          "from": 62,
          "to": 60,
          "distance_m": 16.0,
          "time_s": 1.124999674389098
        },
        {
          "from": 60,
          "to": 43,
          "distance_m": 8.0,
          "time_s": 0.5373941087907369
        },
        {
          "from": 43,
          "to": 42,
          "distance_m": 8.0,
          "time_s": 0.5013687209048373
        },
        {
          "from": 42,
          "to": 41,
          "distance_m": 8.0,
          "time_s": 0.46235374055507483
        },
        {
          "from": 41,
          "to": 40,
          "distance_m": 8.0,
          "time_s": 0.6261130604499712
        },
        {
          "from": 40,
          "to": 39,
          "distance_m": 8.0,
          "time_s": 0.6241769987808401
        },
        {
          "from": 39,
          "to": 38,
          "distance_m": 8.0,
          "time_s": 0.5651524916789967
        },
        {
          "from": 38,
          "to": 35,
          "distance_m": 9.0,
          "time_s": 0.6834189256016778
        },
        {
          "from": 35,
          "to": 36,
          "distance_m": 8.0,
          "time_s": 0.6249905741609884
        },
        {
          "from": 36,
          "to": 37,
          "distance_m": 9.0,
          "time_s": 0.6745930223579767
        },
        {
          "from": 37,
          "to": 50,
          "distance_m": 16.0,
          "time_s": 1.0789526021050682
        },
        {
          "from": 50,
          "to": 51,
          "distance_m": 8.0,
          "time_s": 0.6036888648840439
        },
        {
          "from": 51,
          "to": 52,
          "distance_m": 8.0,
          "time_s": 0.5834769574169937
        },
        {
          "from": 52,
          "to": 49,
          "distance_m": 8.0,
          "time_s": 0.628216552116753
        },
        {
          "from": 49,
          "to": 48,
          "distance_m": 8.0,
          "time_s": 0.549709523143525
        },
        {
          "from": 48,
          "to": 47,
          "distance_m": 8.0,
          "time_s": 0.5908377088510903
        },
        {
          "from": 47,
          "to": 53,
          "distance_m": 11.0,
          "time_s": 0.7606015581855198
        },
        {
          "from": 53,
          "to": 54,
          "distance_m": 8.0,
          "time_s": 0.6223486245484919
        },
        {
          "from": 54,
          "to": 46,
          "distance_m": 11.0,
          "time_s": 0.8923174420786564
        },
        {
          "from": 46,
          "to": 55,
          "distance_m": 8.0,
          "time_s": 0.5029885716417728
        },
        {
          "from": 55,
          "to": 56,
          "distance_m": 8.0,
          "time_s": 0.5849280822428593
        },
        {
          "from": 56,
          "to": 57,
          "distance_m": 8.0,
          "time_s": 0.6202540327216025
        },
        {
          "from": 57,
          "to": 45,
          "distance_m": 11.0,
          "time_s": 0.7690325515319784
        },
        {
          "from": 45,
          "to": 44,
          "distance_m": 8.0,
          "time_s": 0.5777577427568841
        },
        {
          "from": 44,
          "to": 59,
          "distance_m": 8.0,
          "time_s": 0.6785186274241711
        },
        {
          "from": 59,
          "to": 58,
          "distance_m": 8.0,
          "time_s": 0.561029326048908
        },
        {
          "from": 58,
          "to": 68,
          "distance_m": 16.0,
          "time_s": 1.1383608247131993
        },
        {
          "from": 68,
          "to": 69,
          "distance_m": 8.0,
          "time_s": 0.5794764920813127
        },
        {
          "from": 69,
          "to": 67,
          "distance_m": 14.0,
          "time_s": 0.9180962953425267
        },
        {
          "from": 67,
          "to": 70,
          "distance_m": 8.0,
          "time_s": 0.5798254594336435
        },
        {
          "from": 70,
          "to": 71,
          "distance_m": 8.0,
          "time_s": 0.5689076420812919
        },
        {
          "from": 71,
          "to": 72,
          "distance_m": 8.0,
          "time_s": 0.5982874574877699
        },
        {
          "from": 72,
          "to": 73,
          "distance_m": 8.0,
          "time_s": 0.5457588873472118
        },
        {
          "from": 73,
          "to": 74,
          "distance_m": 8.0,
          "time_s": 0.49301608400125674
        },
        {
          "from": 74,
          "to": 75,
          "distance_m": 8.0,
          "time_s": 0.59277492331584
        },
        {
          "from": 75,
          "to": 77,
          "distance_m": 8.0,
          "time_s": 0.5483822977247457
        },
        {
          "from": 77,
          "to": 78,
          "distance_m": 8.0,
          "time_s": 0.5968558470461854
        },
        {
          "from": 78,
          "to": 76,
          "distance_m": 18.0,
          "time_s": 1.31480780614291
        },
        {
          "from": 76,
          "to": 84,
          "distance_m": 23.0,
          "time_s": 1.7318010598549964
        },
        {
          "from": 84,
          "to": 87,
          "distance_m": 8.0,
          "time_s": 0.6870816189295703
        },
        {
          "from": 87,
          "to": 113,
          "distance_m": 8.0,
          "time_s": 0.5732552268181088
        },
        {
          "from": 113,
          "to": 114,
          "distance_m": 8.0,
          "time_s": 0.5041733278057183
        },
        {
          "from": 114,
          "to": 111,
          "distance_m": 8.0,
          "time_s": 0.5712111495363306
        },
        {
          "from": 111,
          "to": 112,
          "distance_m": 8.0,
          "time_s": 0.5725313695669217
        },
        {
          "from": 112,
          "to": 110,
          "distance_m": 10.0,
          "time_s": 0.8175050632991123
        },
        {
          "from": 110,
          "to": 108,
          "distance_m": 8.0,
          "time_s": 0.6645940204511103
        },
        {
          "from": 108,
          "to": 109,
          "distance_m": 8.0,
          "time_s": 0.5338478265481228
        },
        {
          "from": 109,
          "to": 88,
          "distance_m": 14.0,
          "time_s": 0.9190549636637992
        },
        {
          "from": 88,
          "to": 83,
          "distance_m": 8.0,
          "time_s": 0.604978599234411
        },
        {
          "from": 83,
          "to": 82,
          "distance_m": 8.0,
          "time_s": 0.5543288458677507
        },
        {
          "from": 82,
          "to": 79,
          "distance_m": 14.0,
          "time_s": 1.04116202527549
        },
        {
          "from": 79,
          "to": 80,
          "distance_m": 9.0,
          "time_s": 0.5861097988285847
        },
        {
          "from": 80,
          "to": 81,
          "distance_m": 8.0,
          "time_s": 0.5992015986479278
        },
        {
          "from": 81,
          "to": 89,
          "distance_m": 8.0,
          "time_s": 0.6023169556979716
        },
        {
          "from": 89,
          "to": 90,
          "distance_m": 9.0,
          "time_s": 0.6368889660215482
        },
        {
          "from": 90,
          "to": 91,
          "distance_m": 8.0,
          "time_s": 0.5235799387666366
        },
        {
          "from": 91,
          "to": 92,
          "distance_m": 8.0,
          "time_s": 0.5274848321238753
        },
        {
          "from": 92,
          "to": 93,
          "distance_m": 12.0,
          "time_s": 0.878592288365829
        },
        {
          "from": 93,
          "to": 94,
          "distance_m": 8.0,
          "time_s": 0.6241234741353935
        },
        {
          "from": 94,
          "to": 95,
          "distance_m": 8.0,
          "time_s": 0.5232265265250488
        },
        {
          "from": 95,
          "to": 96,
          "distance_m": 8.0,
          "time_s": 0.5910357669216291
        },
        {
          "from": 96,
          "to": 97,
          "distance_m": 8.0,
          "time_s": 0.5692548243904996
        },
        {
          "from": 97,
          "to": 98,
          "distance_m": 8.0,
          "time_s": 0.49535257065838356
        },
        {
          "from": 98,
          "to": 99,
          "distance_m": 13.0,
          "time_s": 0.9128063690239643
        },
        {
          "from": 99,
          "to": 100,
          "distance_m": 12.0,
          "time_s": 0.876171976449861
        },
        {
          "from": 100,
          "to": 101,
          "distance_m": 8.0,
          "time_s": 0.6166285317926135
        },
        {
          "from": 101,
          "to": 102,
          "distance_m": 8.0,
          "time_s": 0.5353008794524392
        },
        {
          "from": 102,
          "to": 103,
          "distance_m": 8.0,
          "time_s": 0.645020634945775
        },
        {
          "from": 103,
          "to": 104,
          "distance_m": 8.0,
          "time_s": 0.5989553046486535
        },
        {
          "from": 104,
          "to": 105,
          "distance_m": 8.0,
          "time_s": 0.5850816864781584
        },
        {
          "from": 105,
          "to": 106,
          "distance_m": 8.0,
          "time_s": 0.5784731162002066
        },
        {
          "from": 106,
          "to": 107,
          "distance_m": 8.0,
          "time_s": 0.5472365504038298
        },
        {
          "from": 107,
          "to": 174,
          "distance_m": 16.0,
          "time_s": 1.2462704822398984
        },
        {
          "from": 174,
          "to": 173,
          "distance_m": 11.0,
          "time_s": 0.9022632233064733
        },
        {
          "from": 173,
          "to": 171,
          "distance_m": 16.0,
          "time_s": 1.1833841311076283
        },
        {
          "from": 171,
          "to": 172,
          "distance_m": 0.0,
          "time_s": 0.0
        },
        {
          "from": 172,
          "to": 170,
          "distance_m": 8.0,
          "time_s": 0.5838797547482562
        },
        {
          "from": 170,
          "to": 169,
          "distance_m": 9.0,
          "time_s": 0.6149902893015109
        },
        {
          "from": 169,
          "to": 168,
          "distance_m": 14.0,
          "time_s": 1.0268883527961883
        },
        {
          "from": 168,
          "to": 167,
          "distance_m": 8.0,
          "time_s": 0.5368213987462029
        },
        {
          "from": 167,
          "to": 166,
          "distance_m": 12.0,
          "time_s": 0.9995712194571307
        },
        {
          "from": 166,
          "to": 165,
          "distance_m": 14.0,
          "time_s": 0.8529957346674193
        },
        {
          "from": 165,
          "to": 164,
          "distance_m": 8.0,
          "time_s": 0.6606833525893036
        },
        {
          "from": 164,
          "to": 163,
          "distance_m": 8.0,
          "time_s": 0.5593734491145619
        },
        {
          "from": 163,
          "to": 162,
          "distance_m": 8.0,
          "time_s": 0.5255396079860235
        },
        {
          "from": 162,
          "to": 161,
          "distance_m": 8.0,
          "time_s": 0.6328869545338607
        },
        {
          "from": 161,
          "to": 175,
          "distance_m": 8.0,
          "time_s": 0.5833223869358894
        },
        {
          "from": 175,
          "to": 160,
          "distance_m": 8.0,
          "time_s": 0.6123836684900026
        },
        {
          "from": 160,
          "to": 159,
          "distance_m": 8.0,
          "time_s": 0.6435165571206608
        },
        {
          "from": 159,
          "to": 158,
          "distance_m": 8.0,
          "time_s": 0.6148812609197255
        },
        {
          "from": 158,
          "to": 157,
          "distance_m": 8.0,
          "time_s": 0.6286541945736609
        },
        {
          "from": 157,
          "to": 119,
          "distance_m": 8.0,
          "time_s": 0.5683145488365042
        },
        {
          "from": 119,
          "to": 120,
          "distance_m": 8.0,
          "time_s": 0.5512719843022799
        },
        {
          "from": 120,
          "to": 121,
          "distance_m": 8.0,
          "time_s": 0.5823850623520023
        },
        {
          "from": 121,
          "to": 122,
          "distance_m": 8.0,
          "time_s": 0.5349478736964964
        },
        {
          "from": 122,
          "to": 123,
          "distance_m": 8.0,
          "time_s": 0.5331213318989608
        },
        {
          "from": 123,
          "to": 124,
          "distance_m": 8.0,
          "time_s": 0.4848522835186666
        },
        {
          "from": 124,
          "to": 125,
          "distance_m": 8.0,
          "time_s": 0.6189170347569909
        },
        {
          "from": 125,
          "to": 126,
          "distance_m": 12.0,
          "time_s": 0.8161648039235216
        },
        {
          "from": 126,
          "to": 127,
          "distance_m": 8.0,
          "time_s": 0.5476493373951669
        },
        {
          "from": 127,
          "to": 128,
          "distance_m": 8.0,
          "time_s": 0.6196580540362576
        },
        {
          "from": 128,
          "to": 21,
          "distance_m": 8.0,
          "time_s": 0.5623110633872329
        },
        {
          "from": 21,
          "to": 20,
          "distance_m": 8.0,
          "time_s": 0.5560259201809934
        },
        {
          "from": 20,
          "to": 19,
          "distance_m": 8.0,
          "time_s": 0.575873305350937
        },
        {
          "from": 19,
          "to": 18,
          "distance_m": 8.0,
          "time_s": 0.6254449849514847
        },
        {
          "from": 18,
          "to": 17,
          "distance_m": 8.0,
          "time_s": 0.5606455217639219
        },
        {
          "from": 17,
          "to": 133,
          "distance_m": 11.0,
          "time_s": 0.7792211659933728
        },
        {
          "from": 133,
          "to": 132,
          "distance_m": 8.0,
          "time_s": 0.5531355457990712
        },
        {
          "from": 132,
          "to": 131,
          "distance_m": 8.0,
          "time_s": 0.6290402898789696
        },
        {
          "from": 131,
          "to": 130,
          "distance_m": 8.0,
          "time_s": 0.6197790910566415
        },
        {
          "from": 130,
          "to": 129,
          "distance_m": 8.0,
          "time_s": 0.5618920052823511
        },
        {
          "from": 129,
          "to": 154,
          "distance_m": 14.0,
          "time_s": 1.0664727659817295
        },
        {
          "from": 154,
          "to": 155,
          "distance_m": 8.0,
          "time_s": 0.5689931690987329
        },
        {
          "from": 155,
          "to": 153,
          "distance_m": 8.0,
          "time_s": 0.6075227734399117
        },
        {
          "from": 153,
          "to": 156,
          "distance_m": 8.0,
          "time_s": 0.5721994993980066
        },
        {
          "from": 156,
          "to": 152,
          "distance_m": 8.0,
          "time_s": 0.6103683444216961
        },
        {
          "from": 152,
          "to": 151,
          "distance_m": 8.0,
          "time_s": 0.5425028525413506
        },
        {
          "from": 151,
          "to": 177,
          "distance_m": 8.0,
          "time_s": 0.5293390649939755
        },
        {
          "from": 177,
          "to": 176,
          "distance_m": 8.0,
          "time_s": 0.5989657620048282
        },
        {
          "from": 176,
          "to": 181,
          "distance_m": 8.0,
          "time_s": 0.6413229657887045
        },
        {
          "from": 181,
          "to": 182,
          "distance_m": 8.0,
          "time_s": 0.6693537192201966
        },
        {
          "from": 182,
          "to": 183,
          "distance_m": 8.0,
          "time_s": 0.6437992537455632
        },
        {
          "from": 183,
          "to": 184,
          "distance_m": 8.0,
          "time_s": 0.5214690215291957
        },
        {
          "from": 184,
          "to": 185,
          "distance_m": 8.0,
          "time_s": 0.549763446263418
        },
        {
          "from": 185,
          "to": 186,
          "distance_m": 11.0,
          "time_s": 0.7567735279933951
        },
        {
          "from": 186,
          "to": 187,
          "distance_m": 8.0,
          "time_s": 0.5871506072713275
        },
        {
          "from": 187,
          "to": 188,
          "distance_m": 13.0,
          "time_s": 0.9399584711004161
        },
        {
          "from": 188,
          "to": 189,
          "distance_m": 8.0,
          "time_s": 0.5791911106843054
        },
        {
          "from": 189,
          "to": 190,
          "distance_m": 8.0,
          "time_s": 0.5563125565499114
        },
        {
          "from": 190,
          "to": 191,
          "distance_m": 12.0,
          "time_s": 0.8238640165866327
        },
        {
          "from": 191,
          "to": 192,
          "distance_m": 14.0,
          "time_s": 1.059426658401838
        },
        {
          "from": 192,
          "to": 193,
          "distance_m": 17.0,
          "time_s": 1.2723334882459238
        },
        {
          "from": 193,
          "to": 197,
          "distance_m": 16.0,
          "time_s": 1.2053449180523181
        },
        {
          "from": 197,
          "to": 194,
          "distance_m": 8.0,
          "time_s": 0.5819005234067735
        },
        {
          "from": 194,
          "to": 195,
          "distance_m": 8.0,
          "time_s": 0.5236973514962612
        },
        {
          "from": 195,
          "to": 196,
          "distance_m": 8.0,
          "time_s": 0.594862770972574
        },
        {
          "from": 196,
          "to": 201,
          "distance_m": 8.0,
          "time_s": 0.6007327374292986
        },
        {
          "from": 201,
          "to": 198,
          "distance_m": 8.0,
          "time_s": 0.5464373101460298
        },
        {
          "from": 198,
          "to": 199,
          "distance_m": 8.0,
          "time_s": 0.5487289588893948
        },
        {
          "from": 199,
          "to": 145,
          "distance_m": 8.0,
          "time_s": 0.5849583992424711
        },
        {
          "from": 145,
          "to": 146,
          "distance_m": 8.0,
          "time_s": 0.5014497311822153
        },
        {
          "from": 146,
          "to": 179,
          "distance_m": 32.0,
          "time_s": 2.6080238624714958
        },
        {
          "from": 179,
          "to": 180,
          "distance_m": 9.0,
          "time_s": 0.5505236966356083
        },
        {
          "from": 180,
          "to": 178,
          "distance_m": 20.0,
          "time_s": 1.3681783647030843
        },
        {
          "from": 178,
          "to": 150,
          "distance_m": 16.0,
          "time_s": 1.1396499061489123
        },
        {
          "from": 150,
          "to": 149,
          "distance_m": 16.0,
          "time_s": 1.2358289941154563
        },
        {
          "from": 149,
          "to": 139,
          "distance_m": 9.0,
          "time_s": 0.608373651235833
        },
        {
          "from": 139,
          "to": 140,
          "distance_m": 8.0,
          "time_s": 0.6144921695389549
        },
        {
          "from": 140,
          "to": 141,
          "distance_m": 8.0,
          "time_s": 0.6243812850166605
        },
        {
          "from": 141,
          "to": 148,
          "distance_m": 8.0,
          "time_s": 0.617239452210205
        },
        {
          "from": 148,
          "to": 147,
          "distance_m": 8.0,
          "time_s": 0.629656213394478
        },
        {
          "from": 147,
          "to": 142,
          "distance_m": 8.0,
          "time_s": 0.5418851858729447
        },
        {
          "from": 142,
          "to": 143,
          "distance_m": 8.0,
          "time_s": 0.5206972304913892
        },
        {
          "from": 143,
          "to": 144,
          "distance_m": 8.0,
          "time_s": 0.5401154061487786
        },
        {
          "from": 144,
          "to": 200,
          "distance_m": 8.0,
          "time_s": 0.5745714920356813
        },
        {
          "from": 200,
          "to": 202,
          "distance_m": 9.0,
          "time_s": 0.7224602289492523
        },
        {
          "from": 202,
          "to": 203,
          "distance_m": 11.0,
          "time_s": 0.7301165518178684
        },
        {
          "from": 203,
          "to": 204,
          "distance_m": 11.0,
          "time_s": 0.8355192354623829
        },
        {
          "from": 204,
          "to": 205,
          "distance_m": 11.0,
          "time_s": 0.8549081081835
        },
        {
          "from": 205,
          "to": 206,
          "distance_m": 11.0,
          "time_s": 0.8018707207250401
        },
        {
          "from": 206,
          "to": 208,
          "distance_m": 9.0,
          "time_s": 0.6338703504386336
        },
        {
          "from": 208,
          "to": 207,
          "distance_m": 8.0,
          "time_s": 0.5874134062108812
        },
        {
          "from": 207,
          "to": 212,
          "distance_m": 8.0,
          "time_s": 0.5213464656244373
        },
        {
          "from": 212,
          "to": 211,
          "distance_m": 8.0,
          "time_s": 0.553964646047276
        },
        {
          "from": 211,
          "to": 214,
          "distance_m": 8.0,
          "time_s": 0.5962850904237332
        },
        {
          "from": 214,
          "to": 213,
          "distance_m": 8.0,
          "time_s": 0.5602947731635626
        },
        {
          "from": 213,
          "to": 215,
          "distance_m": 11.0,
          "time_s": 0.8691224545552205
        },
        {
          "from": 215,
          "to": 218,
          "distance_m": 8.0,
          "time_s": 0.586984561612994
        },
        {
          "from": 218,
          "to": 216,
          "distance_m": 11.0,
          "time_s": 0.7456309021808897
        },
        {
          "from": 216,
          "to": 217,
          "distance_m": 8.0,
          "time_s": 0.6150427322805114
        },
        {
          "from": 217,
          "to": 220,
          "distance_m": 8.0,
          "time_s": 0.6014202335532444
        },
        {
          "from": 220,
          "to": 221,
          "distance_m": 8.0,
          "time_s": 0.6049535678771893
        },
        {
          "from": 221,
          "to": 222,
          "distance_m": 8.0,
          "time_s": 0.5762343795599708
        },
        {
          "from": 222,
          "to": 219,
          "distance_m": 8.0,
          "time_s": 0.5787052554541614
        },
        {
          "from": 219,
          "to": 223,
          "distance_m": 18.0,
          "time_s": 1.3046776801993494
        },
        {
          "from": 223,
          "to": 224,
          "distance_m": 11.0,
          "time_s": 0.7333273208525514
        },
        {
          "from": 224,
          "to": 225,
          "distance_m": 8.0,
          "time_s": 0.6026104869233885
        },
        {
          "from": 225,
          "to": 226,
          "distance_m": 8.0,
          "time_s": 0.5895760554115583
        },
        {
          "from": 226,
          "to": 227,
          "distance_m": 8.0,
          "time_s": 0.5526196669217124
        },
        {
          "from": 227,
          "to": 234,
          "distance_m": 16.0,
          "time_s": 1.1225191426838705
        },
        {
          "from": 234,
          "to": 235,
          "distance_m": 8.0,
          "time_s": 0.5044419973271648
        },
        {
          "from": 235,
          "to": 236,
          "distance_m": 8.0,
          "time_s": 0.5129687984858072
        },
        {
          "from": 236,
          "to": 233,
          "distance_m": 8.0,
          "time_s": 0.5738432762117097
        },
        {
          "from": 233,
          "to": 232,
          "distance_m": 8.0,
          "time_s": 0.5242063265624803
        },
        {
          "from": 232,
          "to": 237,
          "distance_m": 8.0,
          "time_s": 0.5560237672794379
        },
        {
          "from": 237,
          "to": 238,
          "distance_m": 8.0,
          "time_s": 0.6164111720537506
        },
        {
          "from": 238,
          "to": 231,
          "distance_m": 8.0,
          "time_s": 0.5782177589623794
        },
        {
          "from": 231,
          "to": 246,
          "distance_m": 8.0,
          "time_s": 0.5977283118549002
        },
        {
          "from": 246,
          "to": 239,
          "distance_m": 8.0,
          "time_s": 0.5875721876542063
        },
        {
          "from": 239,
          "to": 240,
          "distance_m": 8.0,
          "time_s": 0.5855805438046862
        },
        {
          "from": 240,
          "to": 245,
          "distance_m": 8.0,
          "time_s": 0.5898030070538072
        },
        {
          "from": 245,
          "to": 247,
          "distance_m": 9.0,
          "time_s": 0.7179898323720055
        },
        {
          "from": 247,
          "to": 244,
          "distance_m": 9.0,
          "time_s": 0.6065560067259488
        },
        {
          "from": 244,
          "to": 241,
          "distance_m": 8.0,
          "time_s": 0.5185487702680153
        },
        {
          "from": 241,
          "to": 243,
          "distance_m": 9.0,
          "time_s": 0.6751681412087259
        },
        {
          "from": 243,
          "to": 242,
          "distance_m": 8.0,
          "time_s": 0.5200540040891863
        },
        {
          "from": 242,
          "to": 2,
          "distance_m": 20.0,
          "time_s": 1.3786759740769101
        },
        {
          "from": 2,
          "to": 280,
          "distance_m": 9.0,
          "time_s": 0.6386980805036099
        },
        {
          "from": 280,
          "to": 3,
          "distance_m": 10.0,
          "time_s": 0.6631621435218027
        },
        {
          "from": 3,
          "to": 279,
          "distance_m": 11.0,
          "time_s": 0.7330387044539552
        },
        {
          "from": 279,
          "to": 278,
          "distance_m": 9.0,
          "time_s": 0.6279199682632379
        },
        {
          "from": 278,
          "to": 248,
          "distance_m": 18.0,
          "time_s": 1.333224829046778
        },
        {
          "from": 248,
          "to": 249,
          "distance_m": 11.0,
          "time_s": 0.780706087973991
        },
        {
          "from": 249,
          "to": 250,
          "distance_m": 11.0,
          "time_s": 0.6963525587360894
        },
        {
          "from": 250,
          "to": 251,
          "distance_m": 8.0,
          "time_s": 0.4992772825347963
        },
        {
          "from": 251,
          "to": 230,
          "distance_m": 8.0,
          "time_s": 0.5345227073070247
        },
        {
          "from": 230,
          "to": 229,
          "distance_m": 8.0,
          "time_s": 0.6369671351803626
        },
        {
          "from": 229,
          "to": 228,
          "distance_m": 8.0,
          "time_s": 0.5448636437793791
        },
        {
          "from": 228,
          "to": 210,
          "distance_m": 25.0,
          "time_s": 1.8363010811738514
        },
        {
          "from": 210,
          "to": 209,
          "distance_m": 8.0,
          "time_s": 0.5859817436066654
        },
        {
          "from": 209,
          "to": 252,
          "distance_m": 8.0,
          "time_s": 0.5907529210888932
        },
        {
          "from": 252,
          "to": 253,
          "distance_m": 8.0,
          "time_s": 0.5399988434005042
        },
        {
          "from": 253,
          "to": 254,
          "distance_m": 8.0,
          "time_s": 0.5336699014162245
        },
        {
          "from": 254,
          "to": 255,
          "distance_m": 8.0,
          "time_s": 0.574533529480285
        },
        {
          "from": 255,
          "to": 256,
          "distance_m": 8.0,
          "time_s": 0.5799109571963639
        },
        {
          "from": 256,
          "to": 257,
          "distance_m": 8.0,
          "time_s": 0.6478154436569753
        },
        {
          "from": 257,
          "to": 258,
          "distance_m": 8.0,
          "time_s": 0.4861781727263548
        },
        {
          "from": 258,
          "to": 259,
          "distance_m": 8.0,
          "time_s": 0.5516978832432227
        },
        {
          "from": 259,
          "to": 260,
          "distance_m": 8.0,
          "time_s": 0.5489892351218797
        },
        {
          "from": 260,
          "to": 261,
          "distance_m": 8.0,
          "time_s": 0.47173678773585714
        },
        {
          "from": 261,
          "to": 262,
          "distance_m": 11.0,
          "time_s": 0.8050856443822995
        },
        {
          "from": 262,
          "to": 263,
          "distance_m": 11.0,
          "time_s": 0.8268157786588212
        },
        {
          "from": 263,
          "to": 264,
          "distance_m": 11.0,
          "time_s": 0.7803374029920128
        },
        {
          "from": 264,
          "to": 265,
          "distance_m": 11.0,
          "time_s": 0.9333594395239382
        },
        {
          "from": 265,
          "to": 266,
          "distance_m": 8.0,
          "time_s": 0.5778686686595631
        },
        {
          "from": 266,
          "to": 138,
          "distance_m": 8.0,
          "time_s": 0.5816661732695735
        },
        {
          "from": 138,
          "to": 137,
          "distance_m": 8.0,
          "time_s": 0.6055360987837136
        },
        {
          "from": 137,
          "to": 267,
          "distance_m": 8.0,
          "time_s": 0.5891915294601835
        },
        {
          "from": 267,
          "to": 136,
          "distance_m": 11.0,
          "time_s": 0.7530336061351891
        },
        {
          "from": 136,
          "to": 268,
          "distance_m": 8.0,
          "time_s": 0.6452332248844617
        },
        {
          "from": 268,
          "to": 269,
          "distance_m": 8.0,
          "time_s": 0.5282159480747551
        },
        {
          "from": 269,
          "to": 135,
          "distance_m": 8.0,
          "time_s": 0.5484378859842739
        },
        {
          "from": 135,
          "to": 134,
          "distance_m": 8.0,
          "time_s": 0.5135178125990806
        },
        {
          "from": 134,
          "to": 270,
          "distance_m": 8.0,
          "time_s": 0.5176480372088713
        },
        {
          "from": 270,
          "to": 16,
          "distance_m": 22.0,
          "time_s": 1.6346255656489
        },
        {
          "from": 16,
          "to": 271,
          "distance_m": 8.0,
          "time_s": 0.4935300101976479
        },
        {
          "from": 271,
          "to": 272,
          "distance_m": 8.0,
          "time_s": 0.5420932059504044
        },
        {
          "from": 272,
          "to": 273,
          "distance_m": 8.0,
          "time_s": 0.5614289629374728
        },
        {
          "from": 273,
          "to": 274,
          "distance_m": 8.0,
          "time_s": 0.5664041307760516
        },
        {
          "from": 274,
          "to": 275,
          "distance_m": 8.0,
          "time_s": 0.5867255100631626
        },
        {
          "from": 275,
          "to": 276,
          "distance_m": 8.0,
          "time_s": 0.5564349623844949
        },
        {
          "from": 276,
          "to": 277,
          "distance_m": 11.0,
          "time_s": 0.7835043099357085
        },
        {
          "from": 277,
          "to": 4,
          "distance_m": 10.0,
          "time_s": 0.6944879699204793
        },
        {
          "from": 4,
          "to": 1,
          "distance_m": 33.0,
          "time_s": 2.1638743598950962
        }
      ],
      "distance_m_legs_sum": 2742.0,
      "time_s_legs_sum": 197.76288203792384,
      "distance_m_diff": 0.0,
      "time_s_diff": 0.0
    }
  ]
}